<annotation>
	<folder>MasterImages - Brand</folder>
	<filename>Brand287.jpg</filename>
	<path>/home/chirag/MasterImages - Brand/Brand287.jpg</path>
	<source>
		<database>Unknown</database>
	</source>
	<size>
		<width>4608</width>
		<height>3456</height>
		<depth>3</depth>
	</size>
	<segmented>0</segmented>
	<object>
		<name>Lays</name>
		<pose>Unspecified</pose>
		<truncated>0</truncated>
		<difficult>0</difficult>
		<bndbox>
			<xmin>2087</xmin>
			<ymin>2293</ymin>
			<xmax>2393</xmax>
			<ymax>2525</ymax>
		</bndbox>
	</object>
	<object>
		<name>Lays</name>
		<pose>Unspecified</pose>
		<truncated>0</truncated>
		<difficult>0</difficult>
		<bndbox>
			<xmin>2550</xmin>
			<ymin>1725</ymin>
			<xmax>2908</xmax>
			<ymax>2120</ymax>
		</bndbox>
	</object>
	<object>
		<name>Lays</name>
		<pose>Unspecified</pose>
		<truncated>0</truncated>
		<difficult>0</difficult>
		<bndbox>
			<xmin>2740</xmin>
			<ymin>409</ymin>
			<xmax>3198</xmax>
			<ymax>672</ymax>
		</bndbox>
	</object>
	<object>
		<name>Lays</name>
		<pose>Unspecified</pose>
		<truncated>0</truncated>
		<difficult>0</difficult>
		<bndbox>
			<xmin>1398</xmin>
			<ymin>709</ymin>
			<xmax>1782</xmax>
			<ymax>1109</ymax>
		</bndbox>
	</object>
	<object>
		<name>Lays</name>
		<pose>Unspecified</pose>
		<truncated>0</truncated>
		<difficult>0</difficult>
		<bndbox>
			<xmin>2424</xmin>
			<ymin>1109</ymin>
			<xmax>2814</xmax>
			<ymax>1546</ymax>
		</bndbox>
	</object>
	<object>
		<name>tooyumm</name>
		<pose>Unspecified</pose>
		<truncated>0</truncated>
		<difficult>0</difficult>
		<bndbox>
			<xmin>1798</xmin>
			<ymin>1788</ymin>
			<xmax>2161</xmax>
			<ymax>2067</ymax>
		</bndbox>
	</object>
	<object>
		<name>tooyumm</name>
		<pose>Unspecified</pose>
		<truncated>0</truncated>
		<difficult>0</difficult>
		<bndbox>
			<xmin>1329</xmin>
			<ymin>1246</ymin>
			<xmax>1529</xmax>
			<ymax>1346</ymax>
		</bndbox>
	</object>
	<object>
		<name>tooyumm</name>
		<pose>Unspecified</pose>
		<truncated>0</truncated>
		<difficult>0</difficult>
		<bndbox>
			<xmin>2935</xmin>
			<ymin>1451</ymin>
			<xmax>3266</xmax>
			<ymax>1683</ymax>
		</bndbox>
	</object>
	<object>
		<name>kurkure</name>
		<pose>Unspecified</pose>
		<truncated>0</truncated>
		<difficult>0</difficult>
		<bndbox>
			<xmin>3229</xmin>
			<ymin>1972</ymin>
			<xmax>3587</xmax>
			<ymax>2341</ymax>
		</bndbox>
	</object>
	<object>
		<name>kurkure</name>
		<pose>Unspecified</pose>
		<truncated>0</truncated>
		<difficult>0</difficult>
		<bndbox>
			<xmin>3356</xmin>
			<ymin>1693</ymin>
			<xmax>3561</xmax>
			<ymax>1993</ymax>
		</bndbox>
	</object>
	<object>
		<name>kurkure</name>
		<pose>Unspecified</pose>
		<truncated>0</truncated>
		<difficult>0</difficult>
		<bndbox>
			<xmin>3514</xmin>
			<ymin>1099</ymin>
			<xmax>3750</xmax>
			<ymax>1399</ymax>
		</bndbox>
	</object>
	<object>
		<name>kurkure</name>
		<pose>Unspecified</pose>
		<truncated>0</truncated>
		<difficult>0</difficult>
		<bndbox>
			<xmin>2208</xmin>
			<ymin>341</ymin>
			<xmax>2524</xmax>
			<ymax>488</ymax>
		</bndbox>
	</object>
	<object>
		<name>kurkure</name>
		<pose>Unspecified</pose>
		<truncated>0</truncated>
		<difficult>0</difficult>
		<bndbox>
			<xmin>2129</xmin>
			<ymin>1183</ymin>
			<xmax>2261</xmax>
			<ymax>1430</ymax>
		</bndbox>
	</object>
</annotation>
