<annotation>
	<folder>MasterImages - Brand</folder>
	<filename>Brand299.jpg</filename>
	<path>/home/chirag/MasterImages - Brand/Brand299.jpg</path>
	<source>
		<database>Unknown</database>
	</source>
	<size>
		<width>4608</width>
		<height>3456</height>
		<depth>3</depth>
	</size>
	<segmented>0</segmented>
	<object>
		<name>Bisleri</name>
		<pose>Unspecified</pose>
		<truncated>0</truncated>
		<difficult>0</difficult>
		<bndbox>
			<xmin>2082</xmin>
			<ymin>1767</ymin>
			<xmax>2424</xmax>
			<ymax>2241</ymax>
		</bndbox>
	</object>
	<object>
		<name>Bisleri</name>
		<pose>Unspecified</pose>
		<truncated>0</truncated>
		<difficult>0</difficult>
		<bndbox>
			<xmin>3298</xmin>
			<ymin>2520</ymin>
			<xmax>3714</xmax>
			<ymax>2856</ymax>
		</bndbox>
	</object>
	<object>
		<name>Bisleri</name>
		<pose>Unspecified</pose>
		<truncated>1</truncated>
		<difficult>0</difficult>
		<bndbox>
			<xmin>4040</xmin>
			<ymin>2226</ymin>
			<xmax>4608</xmax>
			<ymax>2546</ymax>
		</bndbox>
	</object>
	<object>
		<name>Bisleri</name>
		<pose>Unspecified</pose>
		<truncated>0</truncated>
		<difficult>0</difficult>
		<bndbox>
			<xmin>2566</xmin>
			<ymin>935</ymin>
			<xmax>2950</xmax>
			<ymax>1141</ymax>
		</bndbox>
	</object>
	<object>
		<name>Coca-Cola</name>
		<pose>Unspecified</pose>
		<truncated>0</truncated>
		<difficult>0</difficult>
		<bndbox>
			<xmin>2471</xmin>
			<ymin>2435</ymin>
			<xmax>2677</xmax>
			<ymax>3051</ymax>
		</bndbox>
	</object>
	<object>
		<name>Coca-Cola</name>
		<pose>Unspecified</pose>
		<truncated>0</truncated>
		<difficult>0</difficult>
		<bndbox>
			<xmin>3293</xmin>
			<ymin>1725</ymin>
			<xmax>3487</xmax>
			<ymax>2056</ymax>
		</bndbox>
	</object>
	<object>
		<name>pepsi</name>
		<pose>Unspecified</pose>
		<truncated>0</truncated>
		<difficult>0</difficult>
		<bndbox>
			<xmin>2087</xmin>
			<ymin>1214</ymin>
			<xmax>2350</xmax>
			<ymax>1667</ymax>
		</bndbox>
	</object>
	<object>
		<name>pepsi</name>
		<pose>Unspecified</pose>
		<truncated>0</truncated>
		<difficult>0</difficult>
		<bndbox>
			<xmin>3545</xmin>
			<ymin>899</ymin>
			<xmax>3856</xmax>
			<ymax>1151</ymax>
		</bndbox>
	</object>
</annotation>
