<annotation>
	<folder>MasterImages - Brand</folder>
	<filename>Brand355.jpg</filename>
	<path>/home/chirag/MasterImages - Brand/Brand355.jpg</path>
	<source>
		<database>Unknown</database>
	</source>
	<size>
		<width>4096</width>
		<height>2304</height>
		<depth>3</depth>
	</size>
	<segmented>0</segmented>
	<object>
		<name>tooyumm</name>
		<pose>Unspecified</pose>
		<truncated>0</truncated>
		<difficult>0</difficult>
		<bndbox>
			<xmin>809</xmin>
			<ymin>449</ymin>
			<xmax>1400</xmax>
			<ymax>1654</ymax>
		</bndbox>
	</object>
</annotation>
